nestpython/__init__.py
nestpython/files.py
nestpython/imports.py
nestpython/main.py
nestpython-1.0.0.dist-info/METADATA
nestpython-1.0.0.dist-info/WHEEL
nestpython-1.0.0.dist-info/top_level.txt
nestpython-1.0.0.dist-info/RECORD
